setup.py
django_longerusernameandemail.egg-info/PKG-INFO
django_longerusernameandemail.egg-info/SOURCES.txt
django_longerusernameandemail.egg-info/dependency_links.txt
django_longerusernameandemail.egg-info/not-zip-safe
django_longerusernameandemail.egg-info/top_level.txt
longerusernameandemail/__init__.py
longerusernameandemail/admin.py
longerusernameandemail/forms.py
longerusernameandemail/models.py
longerusernameandemail/views.py
longerusernameandemail/migrations/0001_initial.py
longerusernameandemail/migrations/__init__.py
longerusernameandemail/tests/__init__.py
longerusernameandemail/tests/urls.py