Metadata-Version: 1.0
Name: django-longerusernameandemail
Version: 0.5.4
Summary: django-longerusernameandemail provides a migration and a monkeypatch to make the django auth.user username and email fields longer, instead of the arbitrarily short 30 and 75 characters.
Home-page: UNKNOWN
Author: UNKNOWN
Author-email: UNKNOWN
License: BSD
Keywords: django long email username migration south
Platform: UNKNOWN
